{
  "name": "my-first-index",
  "defaultScoringProfile": "",
  "fields": [
    {
      "name": "HotelId",
      "type": "Edm.String",
      "searchable": false,
      "filterable": true,
      "retrievable": true,
      "sortable": true,
      "facetable": false,
      "key": true,
      "indexAnalyzer": null,
      "searchAnalyzer": null,
      "analyzer": null,
      "normalizer": null,
      "synonymMaps": []
    },
    {
      "name": "HotelName",
      "type": "Edm.String",
      "searchable": true,
      "filterable": true,
      "retrievable": true,
      "sortable": true,
      "facetable": false,
      "key": false,
      "indexAnalyzer": null,
      "searchAnalyzer": null,
      "analyzer": null,
      "normalizer": null,
      "synonymMaps": []
    },
    {
      "name": "Description",
      "type": "Edm.String",
      "searchable": true,
      "filterable": true,
      "retrievable": true,
      "sortable": true,
      "facetable": false,
      "key": false,
      "indexAnalyzer": null,
      "searchAnalyzer": null,
      "analyzer": null,
      "normalizer": null,
      "synonymMaps": []
    },
    {
      "name": "Description_fr",
      "type": "Edm.String",
      "searchable": true,
      "filterable": true,
      "retrievable": true,
      "sortable": true,
      "facetable": false,
      "key": false,
      "indexAnalyzer": null,
      "searchAnalyzer": null,
      "analyzer": null,
      "normalizer": null,
      "synonymMaps": []
    },
    {
      "name": "Category",
      "type": "Edm.String",
      "searchable": true,
      "filterable": true,
      "retrievable": true,
      "sortable": true,
      "facetable": false,
      "key": false,
      "indexAnalyzer": null,
      "searchAnalyzer": null,
      "analyzer": null,
      "normalizer": null,
      "synonymMaps": []
    },
    {
      "name": "Tags",
      "type": "Collection(Edm.String)",
      "searchable": true,
      "filterable": true,
      "retrievable": true,
      "sortable": false,
      "facetable": false,
      "key": false,
      "indexAnalyzer": null,
      "searchAnalyzer": null,
      "analyzer": null,
      "normalizer": null,
      "synonymMaps": []
    },
    {
      "name": "ParkingIncluded",
      "type": "Edm.String",
      "searchable": true,
      "filterable": true,
      "retrievable": true,
      "sortable": true,
      "facetable": false,
      "key": false,
      "indexAnalyzer": null,
      "searchAnalyzer": null,
      "analyzer": null,
      "normalizer": null,
      "synonymMaps": []
    },
    {
      "name": "LastRenovationDate",
      "type": "Edm.String",
      "searchable": true,
      "filterable": true,
      "retrievable": true,
      "sortable": true,
      "facetable": false,
      "key": false,
      "indexAnalyzer": null,
      "searchAnalyzer": null,
      "analyzer": null,
      "normalizer": null,
      "synonymMaps": []
    },
    {
      "name": "Rating",
      "type": "Edm.String",
      "searchable": true,
      "filterable": true,
      "retrievable": true,
      "sortable": true,
      "facetable": false,
      "key": false,
      "indexAnalyzer": null,
      "searchAnalyzer": null,
      "analyzer": null,
      "normalizer": null,
      "synonymMaps": []
    },
    {
      "name": "StreetAddress",
      "type": "Edm.String",
      "searchable": true,
      "filterable": true,
      "retrievable": true,
      "sortable": true,
      "facetable": false,
      "key": false,
      "indexAnalyzer": null,
      "searchAnalyzer": null,
      "analyzer": null,
      "normalizer": null,
      "synonymMaps": []
    },
    {
      "name": "City",
      "type": "Edm.String",
      "searchable": true,
      "filterable": true,
      "retrievable": true,
      "sortable": true,
      "facetable": false,
      "key": false,
      "indexAnalyzer": null,
      "searchAnalyzer": null,
      "analyzer": null,
      "normalizer": null,
      "synonymMaps": []
    },
    {
      "name": "StateProvince",
      "type": "Edm.String",
      "searchable": true,
      "filterable": true,
      "retrievable": true,
      "sortable": true,
      "facetable": false,
      "key": false,
      "indexAnalyzer": null,
      "searchAnalyzer": null,
      "analyzer": null,
      "normalizer": null,
      "synonymMaps": []
    },
    {
      "name": "PostalCode",
      "type": "Edm.String",
      "searchable": true,
      "filterable": true,
      "retrievable": true,
      "sortable": true,
      "facetable": false,
      "key": false,
      "indexAnalyzer": null,
      "searchAnalyzer": null,
      "analyzer": null,
      "normalizer": null,
      "synonymMaps": []
    },
    {
      "name": "Country",
      "type": "Edm.String",
      "searchable": true,
      "filterable": true,
      "retrievable": true,
      "sortable": true,
      "facetable": false,
      "key": false,
      "indexAnalyzer": null,
      "searchAnalyzer": null,
      "analyzer": null,
      "normalizer": null,
      "synonymMaps": []
    }
  ],
  "scoringProfiles": [],
  "corsOptions": {
    "allowedOrigins": [
      "*"
    ],
    "maxAgeInSeconds": null
  },
  "suggesters": [],
  "analyzers": [],
  "normalizers": [],
  "tokenizers": [],
  "tokenFilters": [],
  "charFilters": [],
  "encryptionKey": null,
  "similarity": {
    "@odata.type": "#Microsoft.Azure.Search.BM25Similarity",
    "k1": null,
    "b": null
  },
  "semantic": {
    "configurations": [
      {
        "name": "semconf",
        "prioritizedFields": {
          "titleField": {
            "fieldName": "HotelName"
          },
          "prioritizedContentFields": [
            {
              "fieldName": "Description"
            }
          ],
          "prioritizedKeywordsFields": [
            {
              "fieldName": "Tags"
            }
          ]
        }
      }
    ]
  }
}